pg_chameleon/__init__.py
pg_chameleon/configuration/config-example.yml
pg_chameleon/lib/__init__.py
pg_chameleon/lib/global_lib.py
pg_chameleon/lib/mysql_lib.py
pg_chameleon/lib/pg_lib.py
pg_chameleon/lib/sql_util.py
pg_chameleon/sql/create_schema.sql
pg_chameleon/sql/drop_schema.sql
pg_chameleon/sql/fn_process_batch.sql
pg_chameleon/sql/fn_replay_data.sql
pg_chameleon/sql/get_fkeys.sql
pg_chameleon/sql/scratch.sql
pg_chameleon/sql/scratch3.sql
pg_chameleon/sql/dev/custom_aggregate.sql
pg_chameleon/sql/dev/fn_parse_json.sql
pg_chameleon/sql/dev/fn_parse_json_2.sql
pg_chameleon/sql/dev/fn_process_batch.sql
pg_chameleon/sql/dev/fn_replay_mysql.sql
pg_chameleon/sql/dev/fn_replay_mysql_v3.sql
pg_chameleon/sql/dev/fn_replay_mysql_v3_stream.sql
pg_chameleon/sql/tests/01_create.sql
pg_chameleon/sql/tests/02_insert.sql
pg_chameleon/sql/tests/03_update.sql
pg_chameleon/sql/tests/04_delete.sql
pg_chameleon/sql/tests/05_drop.sql
pg_chameleon/sql/tests/06_create_broken.sql
pg_chameleon/sql/tests/07_insert_broken.sql
pg_chameleon/sql/tests/08_drop_broken.sql
pg_chameleon/sql/tests/09_alter.sql
pg_chameleon/sql/tests/10_insert_expanded.sql
pg_chameleon/sql/tests/fn_load_data.sql
pg_chameleon/sql/tests/get_default_val.sql
pg_chameleon/sql/tests/test.sql
pg_chameleon/sql/tests/test_pkeyless.sql
pg_chameleon/sql/tests/wrong_log_position.sql
pg_chameleon/sql/upgrade/.placeholder
pg_chameleon/sql/upgrade/200_to_201.sql
pg_chameleon/sql/upgrade/201_to_202.sql
pg_chameleon/sql/upgrade/202_to_203.sql
pg_chameleon/sql/upgrade/203_to_204.sql
pg_chameleon/sql/upgrade/204_to_205.sql
pg_chameleon/sql/upgrade/205_to_206.sql
pg_chameleon/sql/upgrade/206_to_207.sql
pg_chameleon/sql/upgrade/207_to_208.sql
pg_chameleon/sql/upgrade/208_to_209.sql
pg_chameleon/sql/upgrade/209_to_2010.sql
pg_chameleon-2.0.21.data/scripts/chameleon
pg_chameleon-2.0.21.data/scripts/chameleon.py
pg_chameleon-2.0.21.dist-info/LICENSE.txt
pg_chameleon-2.0.21.dist-info/METADATA
pg_chameleon-2.0.21.dist-info/WHEEL
pg_chameleon-2.0.21.dist-info/top_level.txt
pg_chameleon-2.0.21.dist-info/RECORD
