Metadata-Version: 2.2
Name: pg_chameleon
Version: 2.0.21
Summary: MySQL to PostgreSQL replica and migration
Home-page: https://codeberg.org/the4thdoctor/pg_chameleon
Author: Federico Campoli
Author-email: thedoctor@pgdba.org
Maintainer: Federico Campoli
Maintainer-email: thedoctor@pgdba.org
License: BSD License
Keywords: postgresql mysql replica migration database
Platform: linux
Classifier: License :: OSI Approved :: BSD License
Classifier: Environment :: Console
Classifier: Intended Audience :: Developers
Classifier: Intended Audience :: Information Technology
Classifier: Intended Audience :: System Administrators
Classifier: Natural Language :: English
Classifier: Operating System :: POSIX :: BSD
Classifier: Operating System :: POSIX :: Linux
Classifier: Programming Language :: Python
Classifier: Programming Language :: Python :: 3
Classifier: Topic :: Database :: Database Engines/Servers
Classifier: Topic :: Other/Nonlisted Topic
Requires-Python: >=3.7
License-File: LICENSE.txt
Requires-Dist: PyMySQL>=0.10.0
Requires-Dist: mysql-replication>=0.31
Requires-Dist: psycopg2-binary>=2.8.3
Requires-Dist: PyYAML>=3.13
Requires-Dist: tabulate>=0.8.1
Requires-Dist: daemonize>=2.4.7
Requires-Dist: rollbar>=0.13.17
Requires-Dist: parsy>=2.1
Requires-Dist: Sphinx>=7.4.7
Dynamic: author
Dynamic: author-email
Dynamic: classifier
Dynamic: description
Dynamic: home-page
Dynamic: keywords
Dynamic: license
Dynamic: maintainer
Dynamic: maintainer-email
Dynamic: platform
Dynamic: requires-dist
Dynamic: requires-python
Dynamic: summary
